ScratchExtensionTools/__init__.py
scratchextensiontools-1.2.2.dist-info/LICENSE
scratchextensiontools-1.2.2.dist-info/METADATA
scratchextensiontools-1.2.2.dist-info/WHEEL
scratchextensiontools-1.2.2.dist-info/RECORD
