Metadata-Version: 2.3
Name: ScratchExtensionTools
Version: 1.2.2
Summary: Tools to help build Scratch extensions in Python.
License: MIT
Keywords: scratch,extension,builder,pscript
Author: qiufeng
Author-email: appleidqiufeng@outlook.com
Requires-Python: >=3.8,<4.0
Classifier: License :: OSI Approved :: MIT License
Classifier: Operating System :: OS Independent
Classifier: Programming Language :: Python :: 3
Classifier: Programming Language :: Python :: 3.8
Classifier: Programming Language :: Python :: 3.9
Classifier: Programming Language :: Python :: 3.10
Classifier: Programming Language :: Python :: 3.11
Classifier: Programming Language :: Python :: 3.12
Classifier: Programming Language :: Python :: 3.13
Requires-Dist: pscript (>=0.7,<1.0)
Project-URL: Changelog, https://github.com/qiufengcute/ScratchExtensionTools/blob/main/CHANGELOG.md
Project-URL: Homepage, https://github.com/qiufengcute/ScratchExtensionTools
Project-URL: Repository, https://github.com/qiufengcute/ScratchExtensionTools
